falco_ui/__about__.py
falco_ui/__init__.py
falco_ui/apps.py
falco_ui/py.typed
falco_ui/urls.py
falco_ui/views.py
falco_ui/templates/allauth/elements/alert.html
falco_ui/templates/allauth/elements/badge.html
falco_ui/templates/allauth/elements/button.html
falco_ui/templates/allauth/elements/button_group.html
falco_ui/templates/allauth/elements/field.html
falco_ui/templates/allauth/elements/fields.html
falco_ui/templates/allauth/elements/form.html
falco_ui/templates/allauth/elements/h1.html
falco_ui/templates/allauth/elements/h2.html
falco_ui/templates/allauth/elements/hr.html
falco_ui/templates/allauth/elements/img.html
falco_ui/templates/allauth/elements/p.html
falco_ui/templates/allauth/elements/panel.html
falco_ui/templates/allauth/elements/provider.html
falco_ui/templates/allauth/elements/provider_list.html
falco_ui/templates/allauth/elements/table.html
falco_ui/templates/allauth/elements/tbody.html
falco_ui/templates/allauth/elements/td.html
falco_ui/templates/allauth/elements/th.html
falco_ui/templates/allauth/elements/thead.html
falco_ui/templates/allauth/elements/tr.html
falco_ui/templates/allauth/layouts/entrance.html
falco_ui/templates/allauth/layouts/manage.html
falco_ui/templatetags/__init__.py
falco_ui/templatetags/falco_ui.py
falco_ui-0.2.0.dist-info/METADATA
falco_ui-0.2.0.dist-info/WHEEL
falco_ui-0.2.0.dist-info/licenses/LICENSE.txt
falco_ui-0.2.0.dist-info/RECORD
