Metadata-Version: 2.3
Name: falco-ui
Version: 0.2.0
Project-URL: Documentation, https://github.com/falcopackages/falco-ui#readme
Project-URL: Issues, https://github.com/falcopackages/falco-ui/issues
Project-URL: Source, https://github.com/falcopackages/falco-ui
Author-email: Tobi DEGNON <tobidegnon@proton.me>
License-Expression: MIT
License-File: LICENSE.txt
Classifier: Development Status :: 4 - Beta
Classifier: Programming Language :: Python
Classifier: Programming Language :: Python :: 3.8
Classifier: Programming Language :: Python :: 3.9
Classifier: Programming Language :: Python :: 3.10
Classifier: Programming Language :: Python :: 3.11
Classifier: Programming Language :: Python :: 3.12
Classifier: Programming Language :: Python :: Implementation :: CPython
Classifier: Programming Language :: Python :: Implementation :: PyPy
Requires-Python: >=3.10
Requires-Dist: falco-app
